Metadata-Version: 2.1
Name: type3detect
Version: 0.0.3
Summary: tools to process the lofar solar data
Home-page: https://github.com/peijin94/type3detect
Download-URL: https://github.com/peijin94/type3detect/archive/refs/heads/master.zip
Author: Peijin
Author-email: pjer1316@gmail.com
License: MIT
Keywords: LOFAR,Solar,radio
Classifier: Development Status :: 4 - Beta
Classifier: Intended Audience :: Developers
Classifier: Topic :: Software Development :: Build Tools
Classifier: License :: OSI Approved :: MIT License
Classifier: Programming Language :: Python :: 3.9
